LICENSE
MANIFEST.in
README.md
setup.py
src/ea/__init__.py
src/ea/sutadapters/__init__.py
src/ea/sutadapters/GUI/__init__.py
src/ea/sutadapters/GUI/android_adb.py
src/ea/sutadapters/GUI/selenium_rc.py
src/ea/sutadapters/GUI/sikuli.py
src/ea/sutadapters/GUI/templates.py
src/ea/sutadapters/GUI/deps/pip_list.txt
src/ea/sutadapters/GUI/deps/yum_list.txt
src/ea/var/tests/1/actions/selenium/clickelement.yml
src/ea/var/tests/1/actions/selenium/closebrowser.yml
src/ea/var/tests/1/actions/selenium/openbrowser.yml
src/ea/var/tests/1/actions/selenium/typetext.yml
src/ea/var/tests/1/actions/selenium/waitelement.yml
src/ea/var/tests/1/actions/sikulix/get_text_clipboard.yml
src/ea/var/tests/1/actions/sikulix/run_code.yml
src/ea/var/tests/1/actions/sikulix/type_path.yml
src/ea/var/tests/1/actions/sikulix/type_shorcut.yml
src/ea/var/tests/1/actions/sikulix/type_text.yml
src/ea/var/tests/1/deprecated/Samples/Adapter_GUI/01_Application.tux
src/ea/var/tests/1/deprecated/Samples/Adapter_GUI/01_Browser.tux
src/ea/var/tests/1/deprecated/Samples/Adapter_GUI/01_Mobile.tux
src/ea/var/tests/1/deprecated/Samples/Adapter_GUI/Selenium/01_Snippets/01_000 Prepare test data.tux
src/ea/var/tests/1/deprecated/Samples/Adapter_GUI/Selenium/01_Snippets/01_001 Load signin page.tux
src/ea/var/tests/1/deprecated/Samples/Adapter_GUI/Selenium/01_Snippets/01_002 Load page signin_create account.tux
src/ea/var/tests/1/deprecated/Samples/Adapter_GUI/Selenium/01_Snippets/01_003 Configure page signin_create account.tux
src/ea/var/tests/1/deprecated/Samples/Adapter_GUI/Selenium/01_Snippets/01_004 Configure page signin_create account_privacy terms_cancel.tux
src/ea/var/tests/1/deprecated/Samples/Adapter_GUI/Selenium/01_Snippets/01_005 Configure page signin_create account -- Selenium2.tux
src/ea/var/tests/1/deprecated/Samples/Adapter_GUI/Selenium/01_Snippets/01_006 Multi_session.tux
src/ea/var/tests/1/deprecated/Samples/Adapter_GUI/Selenium/02_TestsPlan/02_001 Open browser_load google.tpx
src/extensiveautomation_plugin_gui.egg-info/PKG-INFO
src/extensiveautomation_plugin_gui.egg-info/SOURCES.txt
src/extensiveautomation_plugin_gui.egg-info/dependency_links.txt
src/extensiveautomation_plugin_gui.egg-info/requires.txt
src/extensiveautomation_plugin_gui.egg-info/top_level.txt